src/__init__.py
src/constants.py
src/exceptions.py
src/main.py
src/templates/base_structure.json
src/templates/module_structure.json
src/templates/root_structure.json
src/utils/__init__.py
src/utils/input.py
src/utils/structure.py
src/utils/structure_loader.py
src/utils/validation.py
hexarchsetup-0.5.1.dist-info/LICENSE
hexarchsetup-0.5.1.dist-info/METADATA
hexarchsetup-0.5.1.dist-info/WHEEL
hexarchsetup-0.5.1.dist-info/entry_points.txt
hexarchsetup-0.5.1.dist-info/top_level.txt
hexarchsetup-0.5.1.dist-info/RECORD
