Metadata-Version: 2.1
Name: hexarchsetup
Version: 0.5.1
Summary: Automatically generate a hexagonal architecture project structure in Python.         Easily customizable to include user-defined modules.
Author: Éric Dominguez Morales
Author-email: ericdominguezm@gmail.com
Requires-Python: >=3.9
License-File: LICENSE
